{
    "Ar36": {
        "error": 0.00016873327039178048,
        "error_type": "",
        "fit": "previous",
        "references": [
            {
                "exclude": false,
                "record_id": "ba-02-J-785"
            }
        ],
        "value": 0.0020824666326755
    },
    "Ar37": {
        "error": 0.005997625390151716,
        "error_type": "",
        "fit": "previous",
        "references": [
            {
                "exclude": false,
                "record_id": "ba-02-J-785"
            }
        ],
        "value": 0.033179812036754935
    },
    "Ar38": {
        "error": 0.002806613268149503,
        "error_type": "",
        "fit": "previous",
        "references": [
            {
                "exclude": false,
                "record_id": "ba-02-J-785"
            }
        ],
        "value": 0.01170639181755631
    },
    "Ar39": {
        "error": 0.011392626082069934,
        "error_type": "",
        "fit": "previous",
        "references": [
            {
                "exclude": false,
                "record_id": "ba-02-J-785"
            }
        ],
        "value": 0.06550111910903758
    },
    "Ar40": {
        "error": 0.009145225818810334,
        "error_type": "",
        "fit": "previous",
        "references": [
            {
                "exclude": false,
                "record_id": "ba-02-J-785"
            }
        ],
        "value": 0.09933292874541193
    },
    "Ar41": {
        "error": 0.002482188535430442,
        "error_type": "",
        "fit": "previous",
        "references": [
            {
                "exclude": false,
                "record_id": "ba-02-J-785"
            }
        ],
        "value": 0.042335616305615484
    }
}